gmaps_locationshare_api/__init__.py
gmaps_locationshare_api/types.py
gmaps_locationshare_api/utils.py
gmaps_locationshare_api-1.0.2.dist-info/METADATA
gmaps_locationshare_api-1.0.2.dist-info/WHEEL
gmaps_locationshare_api-1.0.2.dist-info/top_level.txt
gmaps_locationshare_api-1.0.2.dist-info/RECORD
