Metadata-Version: 2.1
Name: gmaps_locationshare_api
Version: 1.0.2
Summary: Fully asynchronous (unofficial) API client for Google Map's location share functionality
Author-email: Bowen Feng <857514.leofeng@gmail.com>
Keywords: google,maps,async,client,location,share,location sharing
Classifier: License :: OSI Approved :: MIT License
Classifier: Programming Language :: Python
Classifier: Programming Language :: Python :: 3
Requires-Python: >=3.7
